ciditel_utilities/__init__.py
ciditel_utilities/strings.py
ciditel_utilities/validate.py
utilities_test/__init__.py
utilities_test/ciditel_utilities.py
utilities_test/utilities.py
verificaciones/__init__.py
verificaciones/strings.py
verificaciones/validate.py
ciditel_utilities-0.5.dist-info/LICENSE.txt
ciditel_utilities-0.5.dist-info/METADATA
ciditel_utilities-0.5.dist-info/WHEEL
ciditel_utilities-0.5.dist-info/top_level.txt
ciditel_utilities-0.5.dist-info/RECORD
