Metadata-Version: 2.1
Name: ciditel-utilities
Version: 0.5
Summary: Verificaciones al usuario
License-File: LICENSE.txt
